LICENSE
README.md
mt_html/.env
mt_html/__init__.py
mt_html/cli.py
mt_html/creds.py
mt_html/dump_folder_gen.py
mt_html/env_creator.py
mt_html/mt_code.py
mikrotik_html_documentation-0.1.3rc0.dist-info/entry_points.txt
mikrotik_html_documentation-0.1.3rc0.dist-info/LICENSE
mikrotik_html_documentation-0.1.3rc0.dist-info/WHEEL
mikrotik_html_documentation-0.1.3rc0.dist-info/METADATA
mikrotik_html_documentation-0.1.3rc0.dist-info/RECORD
