Metadata-Version: 2.1
Name: mikrotik-html-documentation
Version: 0.1.3rc0
Summary: Mikrotik Config to Markup
Home-page: https://github.com/purplecomputer/Mikrotik_HTML_Documentation
License: Apache-2.0
Keywords: mikrotik,mikrotik-documentation
Author: Angelo Poggi
Author-email: angelo.poggi@opti9tech.com
Requires-Python: >=3.8,<4.0
Classifier: License :: OSI Approved :: Apache Software License
Classifier: Programming Language :: Python :: 3
Classifier: Programming Language :: Python :: 3.10
Classifier: Programming Language :: Python :: 3.8
Classifier: Programming Language :: Python :: 3.9
Requires-Dist: RouterOS-api (==0.17.0)
Requires-Dist: click (>=8.0.3,<9.0.0)
Requires-Dist: json2html (>=1.3.0,<2.0.0)
Requires-Dist: python-dotenv (>=0.19.2,<0.20.0)
Project-URL: Repository, https://github.com/purplecomputer/Mikrotik_HTML_Documentation
